kite_bracket_orders/__init__.py
kite_bracket_orders/alerts.py
kite_bracket_orders/auth.py
kite_bracket_orders/core.py
kite_bracket_orders/dashboard.py
kite_bracket_orders/dependency_check.py
kite_bracket_orders/pipupgrade.py
kite_bracket_orders/sample order.py
kite_bracket_orders/utils.py
kite_order-0.2.1.dist-info/METADATA
kite_order-0.2.1.dist-info/WHEEL
kite_order-0.2.1.dist-info/top_level.txt
kite_order-0.2.1.dist-info/RECORD
