Metadata-Version: 2.4
Name: kite_order
Version: 0.2.1
Summary: A Python module for placing bracket orders with Zerodha's KiteConnect API, featuring authentication, dashboard, Google Sheets integration, and customizable logging.
Author-email: Prasad <mr.xprasadx@gmail.com>
License: MIT
Project-URL: Repository, https://github.com/Prasad1612/kite_bracket_orders
Keywords: zerodha,kiteconnect,trading,bracket-orders,api,google-sheets
Classifier: Programming Language :: Python :: 3
Classifier: License :: OSI Approved :: MIT License
Classifier: Operating System :: OS Independent
Requires-Python: >=3.6
Requires-Dist: kiteconnect>=3.0.0
Requires-Dist: gspread>=5.0.0
Requires-Dist: oauth2client>=4.0.0
Requires-Dist: colorama>=0.4.0
